[
  {
    "eyebrow": "CALIDAD GARANTIZADA",
    "title": "Materiales de primera calidad y durabilidad",
    "subtitle": "Máxima Aislación y calidad de excelencia",
    "description": [
      "Solo utilizamos materiales certificados para asegurar durabilidad y confort.",
      "Estructuras de acero galvanizado de alta resistencia.",
      "Excelente aislación térmica y acústica.",
      "Garantía extendida en cada proyecto."
    ],
    "image": "/uploads/img-1763066650558-516329817.png",
    "imageAlt": "Casa moderna con Steel Frame",
    "imagePosition": "right"
  },
  {
    "eyebrow": "Materiales de primera calidad y durabilidad",
    "title": "Solidez Estructural",
    "description": [
      "Cero Humedad: Olvidate de las patologías típicas de la construcción tradicional."
    ],
    "image": "/uploads/img-1763066541689-687393562.jpeg",
    "imageAlt": "jared",
    "imagePosition": "left",
    "subtitle": "Materiales de primera calidad y durabilidad"
  }
]