[
  {
    "eyebrow": "CALIDAD GARANTIZADA",
    "title": "Materiales de primera calidad y durabilidad",
    "subtitle": "Garantía de excelencia",
    "description": [
      "Solo utilizamos materiales certificados para asegurar durabilidad y confort.",
      "Estructuras de acero galvanizado de alta resistencia.",
      "Excelente aislación térmica y acústica.",
      "Garantía extendida en cada proyecto."
    ],
    "image": "/images/modern-house.png",
    "imageAlt": "Casa moderna con Steel Frame",
    "imagePosition": "right"
  },
  {
    "eyebrow": "NUEVO",
    "title": "Título de la sección",
    "description": [
      "Descripción de la sección"
    ],
    "image": "/placeholder.svg?height=400&width=600",
    "imageAlt": "Imagen",
    "imagePosition": "right"
  },
  {
    "eyebrow": "aewawda",
    "title": "Título de la sección",
    "description": [
      "asdsada"
    ],
    "image": "/uploads/img-1762634072892-502683297.png",
    "imageAlt": "jared",
    "imagePosition": "left",
    "subtitle": "awdwadawd"
  },
  {
    "eyebrow": "NUEVO",
    "title": "Título de la sección",
    "description": [
      "Descripción de la sección"
    ],
    "image": "/placeholder.svg?height=400&width=600",
    "imageAlt": "Imagen",
    "imagePosition": "right"
  }
]